{"authorDailyContributionsMap":{"joelgoh1":[{"date":"2024-03-07","commitResults":[{"hash":"9d3905f2e16870b7c7fc50b937596d2f2afe86c7","isMergeCommit":false,"messageTitle":"Update README.md","messageBody":"","fileTypesAndContributionMap":{"docs":{"insertions":15,"deletions":11}}},{"hash":"a145970c0f975007724f6ac592aa96c56f791bef","isMergeCommit":false,"messageTitle":"Update Developer Guide","messageBody":"","fileTypesAndContributionMap":{"docs":{"insertions":24,"deletions":12}}}]},{"date":"2024-03-08","commitResults":[{"hash":"eb0d655df51ed9d874ef64ed7434aef16d839a19","isMergeCommit":false,"messageTitle":"Update AboutUs","messageBody":"","fileTypesAndContributionMap":{"docs":{"insertions":51,"deletions":17}}},{"hash":"52b64c07c26b6acd8701174e835175c97752220e","isMergeCommit":true,"messageTitle":"Merge pull request #19 from joelgoh1/Developer-Guide-user-stories","messageBody":"Update Developer Guide","fileTypesAndContributionMap":{}},{"hash":"1fbfd35c642fb80b5cdd72425041acccdfc0a5a9","isMergeCommit":true,"messageTitle":"Merge pull request #22 from joelgoh1/master","messageBody":"Update AboutUs","fileTypesAndContributionMap":{}},{"hash":"0a536b25cd1293a3a977cff9a10814724646564b","isMergeCommit":true,"messageTitle":"Merge pull request #21 from yap-zong-xin/AboutUs","messageBody":"update AboutUs","fileTypesAndContributionMap":{}},{"hash":"bba596d0f8250dff3e15922cc84bf42ea9e857ce","isMergeCommit":false,"messageTitle":"Update image file name","messageBody":"","fileTypesAndContributionMap":{"docs":{"insertions":1,"deletions":1}}},{"hash":"2e2ee8c5f986ad0ff8cd529e0742f54f36103c57","isMergeCommit":true,"messageTitle":"Merge pull request #24 from joelgoh1/master","messageBody":"Update image file name","fileTypesAndContributionMap":{}}]},{"date":"2024-03-12","commitResults":[{"hash":"b41a27fd2ef49d327f6ab3dc79d74ed023f81b8d","isMergeCommit":false,"messageTitle":"Update use cases in Developer Guide","messageBody":"","fileTypesAndContributionMap":{"docs":{"insertions":88,"deletions":27}}}]},{"date":"2024-03-13","commitResults":[{"hash":"81f7d028a57b6f39dc41ea375b206e4fbbdf1427","isMergeCommit":false,"messageTitle":"Correcting for PR comments","messageBody":"","fileTypesAndContributionMap":{"docs":{"insertions":16,"deletions":16}}},{"hash":"57db4494fdffee137c668222a6adb3c98caac6ec","isMergeCommit":true,"messageTitle":"Merge pull request #34 from amanzainal/update-pages","messageBody":"Update AboutUs","fileTypesAndContributionMap":{}}]},{"date":"2024-03-15","commitResults":[{"hash":"ea1af37cbec2565cb34a2285fad8c82d8e41bd2f","isMergeCommit":false,"messageTitle":"Add grade parameter to person","messageBody":"","fileTypesAndContributionMap":{"functional-code":{"insertions":241,"deletions":16},"test-code":{"insertions":73,"deletions":17}}},{"hash":"0e01d9b12466db53a5e4b16fa15b38998f87f297","isMergeCommit":true,"messageTitle":"Merge remote-tracking branch \u0027upstream/master\u0027","messageBody":"# Conflicts:\n#\tdocs/DeveloperGuide.md\n","fileTypesAndContributionMap":{}},{"hash":"14c2f261064b54d40c79fe7a034d09970bf9c1c0","isMergeCommit":true,"messageTitle":"Merge branch \u0027AddGradeParameter\u0027","messageBody":"","fileTypesAndContributionMap":{}}]},{"date":"2024-03-20","commitResults":[{"hash":"674e4995acf43ac155c6ed1e2d9157d8abcd03b0","isMergeCommit":true,"messageTitle":"Merge pull request #42 from joelgoh1/master","messageBody":"Add Grade Parameter to Person","fileTypesAndContributionMap":{}}]},{"date":"2024-03-21","commitResults":[{"hash":"f343775f842f803d7b5a50c46add863daf3b0f57","isMergeCommit":true,"messageTitle":"Merge pull request #44 from amanzainal/view-grades","messageBody":"Display grades when viewing person","tags":["v1.2"],"fileTypesAndContributionMap":{}}]},{"date":"2024-03-22","commitResults":[{"hash":"7b0128d429c50dea5deaf53b9e9e70b31cfaf1d9","isMergeCommit":false,"messageTitle":"Modify add command to include grade parameter","messageBody":"","fileTypesAndContributionMap":{"functional-code":{"insertions":5,"deletions":2}}},{"hash":"1e78f04890852e81c964a02fa6c00ab12875e1c8","isMergeCommit":true,"messageTitle":"Merge pull request #45 from joelgoh1/Add-Command","messageBody":"Modify add command to include grade parameter","fileTypesAndContributionMap":{}},{"hash":"305fe2326eb076a9e31288cc3dc716e7377e1393","isMergeCommit":true,"messageTitle":"Merge pull request #46 from yap-zong-xin/edit-grades","messageBody":"add grades edit","fileTypesAndContributionMap":{}}]},{"date":"2024-03-27","commitResults":[{"hash":"868b27285db81421647be22330eac9ff6ab3f2a0","isMergeCommit":false,"messageTitle":"Refactor to match TutorTrack","messageBody":"","fileTypesAndContributionMap":{"functional-code":{"insertions":634,"deletions":624},"other":{"insertions":243,"deletions":230},"docs":{"insertions":3,"deletions":3},"test-code":{"insertions":953,"deletions":923}}}]},{"date":"2024-03-28","commitResults":[{"hash":"90dccd20758e38dfc704e95643792957ad0a8003","isMergeCommit":false,"messageTitle":"Add filter command","messageBody":"","fileTypesAndContributionMap":{"functional-code":{"insertions":140,"deletions":0},"test-code":{"insertions":135,"deletions":0}}},{"hash":"9eca23e9d0e7341916be67c2f2ba73348d543708","isMergeCommit":false,"messageTitle":"Update UML Diagram","messageBody":"","fileTypesAndContributionMap":{"docs":{"insertions":12,"deletions":12}}},{"hash":"9e95012e5a79f6321f684b40ee0f8ea9e8c1691a","isMergeCommit":false,"messageTitle":"Update documentation","messageBody":"","fileTypesAndContributionMap":{"docs":{"insertions":73,"deletions":5}}},{"hash":"4b3d7f6612ba1652376eb3d0bd1dac450eabcd0a","isMergeCommit":true,"messageTitle":"Merge pull request #52 from joelgoh1/refactor","messageBody":"Refactor to match TutorTrack","fileTypesAndContributionMap":{}},{"hash":"b6fb1778ed772bfd8fda7d35255b28966a41bfab","isMergeCommit":false,"messageTitle":"first commit","messageBody":"","fileTypesAndContributionMap":{"docs":{"insertions":1,"deletions":0}}},{"hash":"96360ba365770f8c304f876a7fa13eb8f35f0298","isMergeCommit":true,"messageTitle":"Merge pull request #58 from joelgoh1/EnableAssertion","messageBody":"Enable Assertions","fileTypesAndContributionMap":{}},{"hash":"1ed72341eb1b27760e04c5ec59088f98d0903e3a","isMergeCommit":false,"messageTitle":"Update version number in MainApp.java","messageBody":"","fileTypesAndContributionMap":{"functional-code":{"insertions":1,"deletions":1},"other":{"insertions":5,"deletions":0}}},{"hash":"dddc79d6e1305f2ad1c98878aa9dde08a708c9f9","isMergeCommit":true,"messageTitle":"Merge pull request #59 from joelgoh1/main","messageBody":"Update version number in MainApp.java","tags":["v1.3.0"],"fileTypesAndContributionMap":{}}]},{"date":"2024-04-04","commitResults":[{"hash":"5eeb02f29694387ccb5de226228a80faab71f25a","isMergeCommit":false,"messageTitle":"Update documentation files","messageBody":"","fileTypesAndContributionMap":{"functional-code":{"insertions":3,"deletions":3},"other":{"insertions":1,"deletions":1},"docs":{"insertions":207,"deletions":139}}},{"hash":"067423467ba655657dc12d6769a6dfa984cc81f6","isMergeCommit":true,"messageTitle":"Merge pull request #65 from joelgoh1/UpdateDocumentation","messageBody":"Update documentation files","fileTypesAndContributionMap":{}},{"hash":"8d9ef3645c131bacd8b08a578f9b447c59cdde98","isMergeCommit":true,"messageTitle":"Merge pull request #66 from amanzainal/sort-command","messageBody":"Sort command","fileTypesAndContributionMap":{}},{"hash":"7f3c1bb3df9de479d2f9284ffe35c619ddb3de68","isMergeCommit":false,"messageTitle":"Edit sort command","messageBody":"","fileTypesAndContributionMap":{"functional-code":{"insertions":88,"deletions":12},"test-code":{"insertions":144,"deletions":2}}}]},{"date":"2024-04-05","commitResults":[{"hash":"f567ade5f56ff39a026f1a3d634301b156c75597","isMergeCommit":false,"messageTitle":"Increase code coverage","messageBody":"","fileTypesAndContributionMap":{"test-code":{"insertions":111,"deletions":0}}},{"hash":"134c61b26d4d31a079e057bc7fe852f8dac7e1ad","isMergeCommit":true,"messageTitle":"Merge pull request #69 from joelgoh1/IncreaseCodeCov","messageBody":"Increase code coverage","fileTypesAndContributionMap":{}},{"hash":"1128698888365009805f53d1e32709c3f9cffab8","isMergeCommit":false,"messageTitle":"Fix small typo","messageBody":"","fileTypesAndContributionMap":{"docs":{"insertions":1,"deletions":1}}},{"hash":"12844f02aab12e34c2724adeb6f4b83b3c5cdb75","isMergeCommit":true,"messageTitle":"Merge pull request #70 from joelgoh1/master","messageBody":"Fix small typo","fileTypesAndContributionMap":{}},{"hash":"b3072b84fd2046841aced23079af4320a4c216de","isMergeCommit":false,"messageTitle":"Fix Developer Guide","messageBody":"","fileTypesAndContributionMap":{"docs":{"insertions":3,"deletions":2}}},{"hash":"0b3e2a71d6e214748302c9ac64a0e60d7d053ba5","isMergeCommit":true,"messageTitle":"Merge pull request #71 from joelgoh1/FixDeveloperGuide","messageBody":"Fix Developer Guide","fileTypesAndContributionMap":{}},{"hash":"308c62ea3cb67361fa345182b8b451057c54223e","isMergeCommit":false,"messageTitle":"Fix indentations","messageBody":"","fileTypesAndContributionMap":{"docs":{"insertions":2,"deletions":2}}},{"hash":"962bb9bae64a1949b4a472a40ad7263e631d4377","isMergeCommit":true,"messageTitle":"Merge remote-tracking branch \u0027origin/master\u0027","messageBody":"","fileTypesAndContributionMap":{}},{"hash":"293875d292e319b60b1e5da36392d12d4ab95cac","isMergeCommit":true,"messageTitle":"Merge pull request #72 from joelgoh1/master","messageBody":"Fix Indentations","fileTypesAndContributionMap":{}},{"hash":"b56d66d132daba06d01ac4c629173a468e6cc7e0","isMergeCommit":false,"messageTitle":"Update a link","messageBody":"","fileTypesAndContributionMap":{"docs":{"insertions":1,"deletions":1}}},{"hash":"00b49cce2cdd43578ffba115e04b1089af7fc0bf","isMergeCommit":true,"messageTitle":"Merge pull request #74 from joelgoh1/master","messageBody":"Update a link","fileTypesAndContributionMap":{}}]},{"date":"2024-04-11","commitResults":[{"hash":"0ff328442a9d64935f904618138f90d6724a9e96","isMergeCommit":false,"messageTitle":"Add timeslot timing constraints","messageBody":"","fileTypesAndContributionMap":{"functional-code":{"insertions":59,"deletions":6}}},{"hash":"08e37eab1456ca32386128e03c662e8f6a2bfc1f","isMergeCommit":true,"messageTitle":"Merge pull request #113 from joelgoh1/BugFixes","messageBody":"Add timeslot timing constraints","fileTypesAndContributionMap":{}}]}],"yap-zong-xin":[{"date":"2024-03-08","commitResults":[{"hash":"49d05c3a0f4c8516d5592079170d9a4e34d5031a","isMergeCommit":false,"messageTitle":"add AboutUs","messageBody":"","fileTypesAndContributionMap":{"docs":{"insertions":0,"deletions":0}}},{"hash":"0a249f22a06beb6322d9079b7de1bb7a437b5dea","isMergeCommit":false,"messageTitle":"add AboutUs","messageBody":"","fileTypesAndContributionMap":{"docs":{"insertions":50,"deletions":23}}},{"hash":"f3238f4865d971e57b0e6e10fd1d82c1ad2921b0","isMergeCommit":false,"messageTitle":"update README to include nice-to-have features","messageBody":"","fileTypesAndContributionMap":{"docs":{"insertions":9,"deletions":2}}},{"hash":"6b7f5b8c2c37b9ce8878819f1b4de8429d6c7a2b","isMergeCommit":true,"messageTitle":"Merge pull request #23 from yap-zong-xin/README","messageBody":"update README to include nice-to-have features","fileTypesAndContributionMap":{}}]},{"date":"2024-03-12","commitResults":[{"hash":"470da522f964cd40a1f3035633dc480c30fd40ed","isMergeCommit":false,"messageTitle":"update Use Cases in DG","messageBody":"","fileTypesAndContributionMap":{"docs":{"insertions":104,"deletions":6}}},{"hash":"a9d06ac41f193358fcca86e68bd8db798aacacac","isMergeCommit":false,"messageTitle":"add non-functional-requirements","messageBody":"","fileTypesAndContributionMap":{"docs":{"insertions":4,"deletions":2}}},{"hash":"ec75edb3d1b1f2e20d91e0a77fb939811ff9935b","isMergeCommit":true,"messageTitle":"Merge pull request #36 from yap-zong-xin/DG-Non-Functional-Requirements","messageBody":"add non-functional-requirements","fileTypesAndContributionMap":{}},{"hash":"06d1b990d11145c83b1d661da1d6ef6ab14455af","isMergeCommit":false,"messageTitle":"update Glossary","messageBody":"","fileTypesAndContributionMap":{"docs":{"insertions":7,"deletions":0}}},{"hash":"d63c84ebb9c98288f978ebfefa52be62d4860b05","isMergeCommit":false,"messageTitle":"update UserGuide edit and find","messageBody":"","fileTypesAndContributionMap":{"docs":{"insertions":7,"deletions":8}}},{"hash":"3e401c09abf3e45df71525a6053ea722643bd4f0","isMergeCommit":true,"messageTitle":"Merge pull request #38 from yap-zong-xin/UG-Edit-and-Search","messageBody":"update UserGuide edit and find","fileTypesAndContributionMap":{}}]},{"date":"2024-03-14","commitResults":[{"hash":"dda08577a56b30be38f0d715ac15b331731dbb7a","isMergeCommit":false,"messageTitle":"Update docs/DeveloperGuide.md","messageBody":"Co-authored-by: Joel Goh \u003c64695851+joelgoh1@users.noreply.github.com\u003e","fileTypesAndContributionMap":{"docs":{"insertions":1,"deletions":1}}},{"hash":"6ff8891fadba1c569b1d739c355269e94fceb74f","isMergeCommit":true,"messageTitle":"Merge pull request #37 from yap-zong-xin/DG-Glossary","messageBody":"update Glossary","fileTypesAndContributionMap":{}},{"hash":"da0933f8958835e0e0438d98c7fd56a073346bb9","isMergeCommit":false,"messageTitle":"update use cases based on feedback 1","messageBody":"","fileTypesAndContributionMap":{"docs":{"insertions":100,"deletions":73}}}]},{"date":"2024-03-15","commitResults":[{"hash":"555481ad95a79c7b2332ad7f2b5da0462f28b121","isMergeCommit":true,"messageTitle":"Merge pull request #39 from yap-zong-xin/DG-Use-Cases","messageBody":"Dg use cases","fileTypesAndContributionMap":{}},{"hash":"c1a8f0b64561ddab691532b8b9baee35aa026460","isMergeCommit":false,"messageTitle":"update DG use cases","messageBody":"","fileTypesAndContributionMap":{"docs":{"insertions":0,"deletions":5}}},{"hash":"00afeb44d08a48fd8be4ab0d7159f9687c77ed82","isMergeCommit":true,"messageTitle":"Merge pull request #40 from yap-zong-xin/DG-Use-Cases","messageBody":"remove pre-conditions for DG use cases","fileTypesAndContributionMap":{}}]},{"date":"2024-03-22","commitResults":[{"hash":"bed1d848caf5271f198d8acc0f247a55d896a429","isMergeCommit":false,"messageTitle":"add grades edit","messageBody":"","fileTypesAndContributionMap":{"functional-code":{"insertions":24,"deletions":4}}},{"hash":"e527e90f117af57d85dca0f524d69a90c4293f60","isMergeCommit":false,"messageTitle":"add test for grade edit","messageBody":"","fileTypesAndContributionMap":{"test-code":{"insertions":13,"deletions":0}}}]},{"date":"2024-03-28","commitResults":[{"hash":"80a21effae08509b4cf36fcc8cff995281f0a3ea","isMergeCommit":false,"messageTitle":"update edit command to take in single variable","messageBody":"","fileTypesAndContributionMap":{"functional-code":{"insertions":259,"deletions":42}}},{"hash":"81588dd6bcf6a1eb0b88959b72ccae764efbc15b","isMergeCommit":false,"messageTitle":"update tag variable to allow removal and addition of tags","messageBody":"","fileTypesAndContributionMap":{"functional-code":{"insertions":51,"deletions":19},"test-code":{"insertions":23,"deletions":23}}},{"hash":"9508deca4fb9e588cabce51a2a38fc8792309a1b","isMergeCommit":false,"messageTitle":"update edit checkstyle","messageBody":"","fileTypesAndContributionMap":{"functional-code":{"insertions":27,"deletions":16}}},{"hash":"d8d4ca1fadf0e730e32c7d0355acb22e48421b5c","isMergeCommit":false,"messageTitle":"update edit checkstyle","messageBody":"","fileTypesAndContributionMap":{"functional-code":{"insertions":10,"deletions":10}}},{"hash":"e529f36c2dfc3508a393dfcb8134e388fd56e0ac","isMergeCommit":false,"messageTitle":"update edit checkstyle","messageBody":"","fileTypesAndContributionMap":{"functional-code":{"insertions":9,"deletions":8}}},{"hash":"18785e805734ec6aab428046c7700e38fc034672","isMergeCommit":false,"messageTitle":"update edit checkstyle","messageBody":"","fileTypesAndContributionMap":{"test-code":{"insertions":69,"deletions":23}}},{"hash":"7a304f3a061f952b2d16095a28521cae9c3a273e","isMergeCommit":false,"messageTitle":"update edit checkstyle","messageBody":"","fileTypesAndContributionMap":{"functional-code":{"insertions":2,"deletions":2}}},{"hash":"577c393e64ee5cfe3bdec9de18f4e6501b2c0f8c","isMergeCommit":false,"messageTitle":"remove all edit test for now","messageBody":"","fileTypesAndContributionMap":{"test-code":{"insertions":0,"deletions":399}}},{"hash":"bd539daaf0362eb1d4e29ccca7b7c20d50fa5260","isMergeCommit":false,"messageTitle":"update commandbox to fix add error","messageBody":"","fileTypesAndContributionMap":{"functional-code":{"insertions":3,"deletions":0}}},{"hash":"5e9bd5f8caf7b9af3cb765efb106e8ec9c42624b","isMergeCommit":true,"messageTitle":"Merge pull request #54 from joelgoh1/filter","messageBody":"Filter command","fileTypesAndContributionMap":{}},{"hash":"aebf5481e98397482aa985432b638bf43672799d","isMergeCommit":true,"messageTitle":"update edit command","messageBody":"","fileTypesAndContributionMap":{}},{"hash":"b12ee7410c9c7f9c3d1279781db999bdb8624ebe","isMergeCommit":true,"messageTitle":"Merge pull request #57 from yap-zong-xin/change-edit-command","messageBody":"Change edit command","fileTypesAndContributionMap":{}},{"hash":"ea875cb1d5b805462a2a254a97f7293aa8b874be","isMergeCommit":false,"messageTitle":"update Developer Guide","messageBody":"","fileTypesAndContributionMap":{"docs":{"insertions":18,"deletions":0}}},{"hash":"8342106a8815532504710e9378ec699ac92e233c","isMergeCommit":true,"messageTitle":"Merge pull request #60 from yap-zong-xin/developer-guide","messageBody":"update Developer Guide","fileTypesAndContributionMap":{}}]},{"date":"2024-03-29","commitResults":[{"hash":"c642368a24b6d86c6f1d2737e406472ccc2f9fd7","isMergeCommit":false,"messageTitle":"update working tag variable","messageBody":"","fileTypesAndContributionMap":{"functional-code":{"insertions":23,"deletions":41}}},{"hash":"7a252db800162b916ef69d413efd307bf2fa4b2a","isMergeCommit":false,"messageTitle":"update checkstyle","messageBody":"","fileTypesAndContributionMap":{"functional-code":{"insertions":2,"deletions":2}}},{"hash":"49593b1c47ac5d30d7ea77cc9c5e3844c2fe9508","isMergeCommit":true,"messageTitle":"Merge pull request #61 from yap-zong-xin/change-edit-command","messageBody":"update working tag variable","fileTypesAndContributionMap":{}}]},{"date":"2024-03-31","commitResults":[{"hash":"3c313f0320528e587c5852b8d96dffeb34ea1363","isMergeCommit":false,"messageTitle":"update grade edit","messageBody":"","fileTypesAndContributionMap":{"functional-code":{"insertions":27,"deletions":71}}},{"hash":"3f5bcbc62708c51941c67be31fd2ef61e23ac774","isMergeCommit":false,"messageTitle":"update checkstyle","messageBody":"","fileTypesAndContributionMap":{"functional-code":{"insertions":0,"deletions":1}}},{"hash":"d27adcffb8f6af3644dbbb77721ada208bde44da","isMergeCommit":true,"messageTitle":"Merge pull request #62 from yap-zong-xin/change-edit-command","messageBody":"update grade edit","fileTypesAndContributionMap":{}},{"hash":"aba9cf84942a1bf36f360a545ac7c0efb207e624","isMergeCommit":false,"messageTitle":"update uml diagram","messageBody":"","fileTypesAndContributionMap":{"docs":{"insertions":70,"deletions":0}}},{"hash":"10febcf1af9824ff0cf108e2ed6090ab95a70114","isMergeCommit":true,"messageTitle":"Merge pull request #63 from yap-zong-xin/UML","messageBody":"update uml diagram","fileTypesAndContributionMap":{}}]},{"date":"2024-04-02","commitResults":[{"hash":"62a5abdbe699e147225a270465ee6816aaab4616","isMergeCommit":false,"messageTitle":"add code coverage for edit","messageBody":"","fileTypesAndContributionMap":{"test-code":{"insertions":443,"deletions":0}}},{"hash":"c9868f68c85871891e2e1eefcd9a3da0f818063a","isMergeCommit":true,"messageTitle":"Merge pull request #64 from yap-zong-xin/change-edit-command","messageBody":"add code coverage for edit","fileTypesAndContributionMap":{}}]},{"date":"2024-04-05","commitResults":[{"hash":"dc1b28d06b31c4dd95217e61622132bdfea7e232","isMergeCommit":false,"messageTitle":"update edit documentation","messageBody":"","fileTypesAndContributionMap":{"docs":{"insertions":22,"deletions":23}}},{"hash":"90d654ddb53faf1d5bfd38a40aff7b84e1542f3f","isMergeCommit":true,"messageTitle":"Merge pull request #68 from yap-zong-xin/documentations","messageBody":"update edit documentation","fileTypesAndContributionMap":{}}]},{"date":"2024-04-09","commitResults":[{"hash":"56291d0935425a822f422521d38bd0bb20c27bf8","isMergeCommit":false,"messageTitle":"update edit error messages","messageBody":"","fileTypesAndContributionMap":{"functional-code":{"insertions":13,"deletions":0}}},{"hash":"8f5f03c9e1d1dc093c2dccbc937225be3aa3ce31","isMergeCommit":false,"messageTitle":"update edit test","messageBody":"","fileTypesAndContributionMap":{"test-code":{"insertions":1,"deletions":1}}},{"hash":"1c82e78d33d46ec0188a7eba81eb40d3a7552fbd","isMergeCommit":true,"messageTitle":"Merge pull request #109 from yap-zong-xin/fix-bugs","messageBody":"update edit error messages","fileTypesAndContributionMap":{}},{"hash":"d2c7d47d26a31d64d603ba57034e05b740dd991f","isMergeCommit":false,"messageTitle":"update bugs on allowing semi-colons in grades","messageBody":"","fileTypesAndContributionMap":{"functional-code":{"insertions":23,"deletions":12}}},{"hash":"7bad7cec115f226213026f299f9be61480cbde00","isMergeCommit":false,"messageTitle":"update checkstyle","messageBody":"","fileTypesAndContributionMap":{"functional-code":{"insertions":0,"deletions":1}}},{"hash":"c8978b10beedc0c18ab9ac94dfb980cf97f0f5b1","isMergeCommit":false,"messageTitle":"update bug-fixes","messageBody":"","fileTypesAndContributionMap":{"functional-code":{"insertions":8,"deletions":5}}},{"hash":"98942ae203a3caaca7bb2fd804117dac34e779b2","isMergeCommit":false,"messageTitle":"update checkstyle","messageBody":"","fileTypesAndContributionMap":{"functional-code":{"insertions":3,"deletions":2}}},{"hash":"665aba6432ce77e0a649c238afdeca5018e1c018","isMergeCommit":true,"messageTitle":"Merge pull request #110 from yap-zong-xin/fix-bugs","messageBody":"update bugs on allowing semi-colons in grades","fileTypesAndContributionMap":{}},{"hash":"613a29a7cf169a2b2d864990c2a172b4f49780cd","isMergeCommit":false,"messageTitle":"update bugs","messageBody":"","fileTypesAndContributionMap":{"functional-code":{"insertions":3,"deletions":7}}},{"hash":"84aebe98989ff698964f6cdc7964090a637f39e6","isMergeCommit":true,"messageTitle":"Merge pull request #111 from yap-zong-xin/fix-bugs","messageBody":"update bugs","fileTypesAndContributionMap":{}},{"hash":"438eb63c49301fb66a2c972664cb54890fefd952","isMergeCommit":false,"messageTitle":"update bugs","messageBody":"","fileTypesAndContributionMap":{"functional-code":{"insertions":15,"deletions":8}}},{"hash":"b916ceaf73aee82ba36d0cce6aa38d6eed1f1e02","isMergeCommit":true,"messageTitle":"Merge pull request #112 from yap-zong-xin/fix-bugs","messageBody":"update bugs","fileTypesAndContributionMap":{}}]}],"amanzainal":[{"date":"2024-03-05","commitResults":[{"hash":"fd5d5934fb5bfa242fd47c280dce718f3fc8df53","isMergeCommit":false,"messageTitle":"Update README.md","messageBody":"Display CodeCov badge","fileTypesAndContributionMap":{"docs":{"insertions":1,"deletions":0}}},{"hash":"c6bfc9feedcf85fb3adb9d8015bd0f792eda2252","isMergeCommit":true,"messageTitle":"Merge pull request #1 from amanzainal/master","messageBody":"Update README.md","fileTypesAndContributionMap":{}},{"hash":"812736e2955769c45257d2e44d0ab2de3a2e62e6","isMergeCommit":true,"messageTitle":"Merge branch \u0027switch-docs-to-markbind\u0027","messageBody":"","fileTypesAndContributionMap":{}},{"hash":"e4f6cb65456483bf09561543b1f4ea19f5b5ab30","isMergeCommit":true,"messageTitle":"Merge remote-tracking branch \u0027origin/master\u0027","messageBody":"","fileTypesAndContributionMap":{}},{"hash":"c3b1d254caebc297a3ab39b0bb4ac8834d6f7102","isMergeCommit":false,"messageTitle":"Update site config","messageBody":"","fileTypesAndContributionMap":{"docs":{"insertions":1,"deletions":1}}},{"hash":"4ea9084dcfbb6ffcda01bdcba6c5e3d9efeea282","isMergeCommit":true,"messageTitle":"Merge pull request #2 from amanzainal/master","messageBody":"Set up MarkBind","fileTypesAndContributionMap":{}}]},{"date":"2024-03-08","commitResults":[{"hash":"38dbd72f1665a8a3a46a7c685504267cde410ab9","isMergeCommit":true,"messageTitle":"Merge remote-tracking branch \u0027upstream/master\u0027","messageBody":"","fileTypesAndContributionMap":{}}]},{"date":"2024-03-11","commitResults":[{"hash":"6e175eafabc2157bfbdab221deabad49c0b53c3c","isMergeCommit":true,"messageTitle":"Merge remote-tracking branch \u0027upstream/master\u0027","messageBody":"","fileTypesAndContributionMap":{}}]},{"date":"2024-03-12","commitResults":[{"hash":"b816d2263b5d4dedd4b963898bf84fb9ffc9cdfc","isMergeCommit":false,"messageTitle":"Update AboutUs","messageBody":"","fileTypesAndContributionMap":{"docs":{"insertions":55,"deletions":0}}}]},{"date":"2024-03-15","commitResults":[{"hash":"157e55daba70c7fb12d1565b6c3ada37ae9f01ee","isMergeCommit":false,"messageTitle":"Add list alias","messageBody":"","fileTypesAndContributionMap":{"docs":{"insertions":2,"deletions":2}}},{"hash":"58e12e5a07ed8f96a61dece616044911a5ec1426","isMergeCommit":false,"messageTitle":"Revert \"Add list alias\" to re-do in separate branch for PR tracking","messageBody":"This reverts commit 157e55daba70c7fb12d1565b6c3ada37ae9f01ee.\n","fileTypesAndContributionMap":{"docs":{"insertions":2,"deletions":2}}}]},{"date":"2024-03-21","commitResults":[{"hash":"401605cb4ea9469a7d06c84868d10a572f30e5f8","isMergeCommit":true,"messageTitle":"Merge remote-tracking branch \u0027upstream/master\u0027","messageBody":"","fileTypesAndContributionMap":{}},{"hash":"d952f5634a87fce36e84a73441af558ca6b51817","isMergeCommit":false,"messageTitle":"Add grades when viewing person","messageBody":"","fileTypesAndContributionMap":{"functional-code":{"insertions":15,"deletions":4}}},{"hash":"4453b90578a1d7b468700796a21f213f9f8435c7","isMergeCommit":false,"messageTitle":"Improve UI","messageBody":"","fileTypesAndContributionMap":{"functional-code":{"insertions":20,"deletions":1}}}]},{"date":"2024-03-28","commitResults":[{"hash":"8a5e387cc5409ebd595b52b395ef6c6798ec7ae1","isMergeCommit":true,"messageTitle":"Merge pull request #56 from joelgoh1/UpdateDGFeatures","messageBody":"Update documentation","fileTypesAndContributionMap":{}},{"hash":"0bce7010ec582abd688b82180825ae629b385985","isMergeCommit":true,"messageTitle":"Merge pull request #55 from joelgoh1/UpdateUMLDiagram","messageBody":"Update uml diagram","fileTypesAndContributionMap":{}},{"hash":"cbeaacd059bd4e164f46f5269cc8f140e9c21a46","isMergeCommit":false,"messageTitle":"Update Person to Student","messageBody":"","fileTypesAndContributionMap":{"docs":{"insertions":17,"deletions":17}}},{"hash":"44068042829ab96b56fc2bbaadaeb9f5dbd1e743","isMergeCommit":false,"messageTitle":"docs: Update UML diagram to include new parameters","messageBody":"- Change \u0027Person\u0027 to \u0027Student\u0027\n- Remove \u0027Tag\u0027 parameter\n- Add \u0027Timeslot\u0027 parameter\n- Add \u0027grade\u0027 parameter\n\nThis commit updates the UML diagram to reflect the changes made in the system. \u0027Person\u0027 has been replaced with \u0027Student\u0027, \u0027Tag\u0027 parameter has been removed, and \u0027Timeslot\u0027 and \u0027grade\u0027 parameters have been added to accommodate new requirements.\n","fileTypesAndContributionMap":{"docs":{"insertions":15,"deletions":13}}},{"hash":"e0a26a5e5338ec7ba0fb98c04061b9c7704830ec","isMergeCommit":false,"messageTitle":"Rename \u0027Person\u0027 to \u0027Student\u0027 throughout the Developer Guide","messageBody":"This commit replaces all occurrences of \u0027Person\u0027 with \u0027Student\u0027 to reflect the terminology more accurately. The change enhances clarity and consistency in the DG.\n","fileTypesAndContributionMap":{"docs":{"insertions":17,"deletions":17}}},{"hash":"98a2f276e4e356552a41c753a591ac511c409c43","isMergeCommit":false,"messageTitle":"docs: Update UML diagram to include new parameters","messageBody":"- Change \u0027Person\u0027 to \u0027Student\u0027\n- Remove \u0027Tag\u0027 parameter\n- Add \u0027Timeslot\u0027 parameter\n- Add \u0027grade\u0027 parameter\n\nThis commit updates the UML diagram to reflect the changes made in the system. \u0027Person\u0027 has been replaced with \u0027Student\u0027, \u0027Tag\u0027 parameter has been removed, and \u0027Timeslot\u0027 and \u0027grade\u0027 parameters have been added to accommodate new requirements.\n","fileTypesAndContributionMap":{"docs":{"insertions":15,"deletions":13}}}]},{"date":"2024-03-29","commitResults":[{"hash":"6e5e2a561721fb3f43fc73e0477132affc401f1a","isMergeCommit":false,"messageTitle":"Initial commit","messageBody":"","fileTypesAndContributionMap":{"functional-code":{"insertions":0,"deletions":0}}}]},{"date":"2024-03-31","commitResults":[{"hash":"1a5e656ae66ac3d16a4464354ad356e61bb90958","isMergeCommit":true,"messageTitle":"Merge remote-tracking branch \u0027upstream/master\u0027 into sort-command","messageBody":"","fileTypesAndContributionMap":{}}]},{"date":"2024-04-04","commitResults":[{"hash":"f11a7c398c8acc974e62dd1c4848fd29b08ad37b","isMergeCommit":false,"messageTitle":"Add minimal sort framework","messageBody":"","fileTypesAndContributionMap":{"functional-code":{"insertions":143,"deletions":1},"test-code":{"insertions":6,"deletions":0}}},{"hash":"95e1d2593ac1c32a5b9d2f478d71ecd6d84b00d9","isMergeCommit":false,"messageTitle":"Fix NullPointerException","messageBody":"","fileTypesAndContributionMap":{"functional-code":{"insertions":5,"deletions":4}}},{"hash":"ea3ec27d08bc991ce6af49cc22481e6f53371f7c","isMergeCommit":true,"messageTitle":"Merge remote-tracking branch \u0027upstream/master\u0027 into sort-command","messageBody":"","fileTypesAndContributionMap":{}},{"hash":"ec01491dd2f213545445c80dd0d665e67107e4a9","isMergeCommit":false,"messageTitle":"Remove trailing whitespaces","messageBody":"","fileTypesAndContributionMap":{"docs":{"insertions":12,"deletions":12}}},{"hash":"7feba3e5b9a5fcd66e848a7d30c47b385bb8669f","isMergeCommit":false,"messageTitle":"Add newline at EOF","messageBody":"","fileTypesAndContributionMap":{"functional-code":{"insertions":1,"deletions":1}}}]},{"date":"2024-04-05","commitResults":[{"hash":"93339859d9559af4f403a1a1d60ec020c5ab691a","isMergeCommit":true,"messageTitle":"Merge pull request #67 from joelgoh1/EditSortCommand","messageBody":"Edit sort command","fileTypesAndContributionMap":{}},{"hash":"7975d9b44d947fe8db5ca318e04055b0d068cfa7","isMergeCommit":true,"messageTitle":"Merge remote-tracking branch \u0027upstream/master\u0027 into update-pages","messageBody":"","fileTypesAndContributionMap":{}},{"hash":"46e27559adbc7dfa6d1d4ec0d81b28a3a0014e4b","isMergeCommit":false,"messageTitle":"Fix Developer Guide displaying incorrect layout","messageBody":"","fileTypesAndContributionMap":{"docs":{"insertions":3,"deletions":2}}},{"hash":"1953f41496345033cb9a6795d0bfb253f2fc8e7a","isMergeCommit":false,"messageTitle":"Add Sort Feature documentation Fix FeatureSequenceDiagram not displaying correctly due to incorrect path","messageBody":"","fileTypesAndContributionMap":{"docs":{"insertions":39,"deletions":1}}},{"hash":"794f593464fa08a94c384379312b386b13e8cfa0","isMergeCommit":false,"messageTitle":"Add class diagram for sort feature","messageBody":"","fileTypesAndContributionMap":{"docs":{"insertions":31,"deletions":3}}},{"hash":"096db28c98db46bb0a5b4ccdaf8bb64fc2aad1c0","isMergeCommit":true,"messageTitle":"Merge branch \u0027update-pages\u0027 of https://github.com/amanzainal/tp into update-pages","messageBody":"","fileTypesAndContributionMap":{}},{"hash":"0de7528207c176ac8536999d2ebf897d0bb8ec8d","isMergeCommit":true,"messageTitle":"Merge branch \u0027master\u0027 into update-pages","messageBody":"","fileTypesAndContributionMap":{}},{"hash":"04fce78bce4e396bc8b4ca2323057393040263da","isMergeCommit":true,"messageTitle":"Merge pull request #73 from amanzainal/update-pages","messageBody":"Add documentation for sort feature","fileTypesAndContributionMap":{}},{"hash":"6a34fbbc45e79f2598776bb8010d96533a697750","isMergeCommit":false,"messageTitle":"Remove trailing whitespaces and add EOF at end of files for checkstyle compliance","messageBody":"","fileTypesAndContributionMap":{"docs":{"insertions":6,"deletions":6}}},{"hash":"60e33835f66c86eb80f5368690e0c053b98db76c","isMergeCommit":true,"messageTitle":"Merge remote-tracking branch \u0027origin/update-pages\u0027 into update-pages","messageBody":"","fileTypesAndContributionMap":{}},{"hash":"ccf9c590277367ceff6efad8310c2d50851424f1","isMergeCommit":false,"messageTitle":"Add Sort Feature user documentation","messageBody":"","fileTypesAndContributionMap":{"docs":{"insertions":15,"deletions":0}}},{"hash":"dc799f68b2a4b0438ef3d17dbedc39b53b52f965","isMergeCommit":true,"messageTitle":"Merge pull request #75 from amanzainal/update-pages","messageBody":"Update pages","tags":["v1.3.1"],"fileTypesAndContributionMap":{}}]}]},"authorFileTypeContributionMap":{"joelgoh1":{"docs":348,"functional-code":1166,"test-code":1382,"other":6},"yap-zong-xin":{"docs":259,"functional-code":362,"test-code":218},"amanzainal":{"docs":152,"functional-code":163,"test-code":3}},"authorContributionVariance":{"joelgoh1":267867.88,"yap-zong-xin":24899.867,"amanzainal":1224.3958},"authorDisplayNameMap":{"joelgoh1":"CS2103-F08-4 JOEL..FENG","yap-zong-xin":"CS2103-F08-4 YAP .. XIN","amanzainal":"CS2103-F08-4 AMAN..IDIN"}}
